fds/__init__.py
fds/sdk/__init__.py
fds/sdk/RecommendationListAPIforDigitalPortals/__init__.py
fds/sdk/RecommendationListAPIforDigitalPortals/api_client.py
fds/sdk/RecommendationListAPIforDigitalPortals/configuration.py
fds/sdk/RecommendationListAPIforDigitalPortals/exceptions.py
fds/sdk/RecommendationListAPIforDigitalPortals/model_utils.py
fds/sdk/RecommendationListAPIforDigitalPortals/rest.py
fds/sdk/RecommendationListAPIforDigitalPortals/api/__init__.py
fds/sdk/RecommendationListAPIforDigitalPortals/api/recommendation_list_api.py
fds/sdk/RecommendationListAPIforDigitalPortals/apis/__init__.py
fds/sdk/RecommendationListAPIforDigitalPortals/model/__init__.py
fds/sdk/RecommendationListAPIforDigitalPortals/model/attributes_member.py
fds/sdk/RecommendationListAPIforDigitalPortals/model/cursor_based_pagination_output_object.py
fds/sdk/RecommendationListAPIforDigitalPortals/model/cursor_based_pagination_output_object_without_total.py
fds/sdk/RecommendationListAPIforDigitalPortals/model/error_meta_object.py
fds/sdk/RecommendationListAPIforDigitalPortals/model/error_object.py
fds/sdk/RecommendationListAPIforDigitalPortals/model/inline_object.py
fds/sdk/RecommendationListAPIforDigitalPortals/model/inline_response200.py
fds/sdk/RecommendationListAPIforDigitalPortals/model/inline_response2001.py
fds/sdk/RecommendationListAPIforDigitalPortals/model/inline_response2001_active_range.py
fds/sdk/RecommendationListAPIforDigitalPortals/model/inline_response2001_data.py
fds/sdk/RecommendationListAPIforDigitalPortals/model/inline_response2002.py
fds/sdk/RecommendationListAPIforDigitalPortals/model/inline_response2002_data.py
fds/sdk/RecommendationListAPIforDigitalPortals/model/inline_response2002_data_instrument.py
fds/sdk/RecommendationListAPIforDigitalPortals/model/inline_response2002_data_recommendation_list.py
fds/sdk/RecommendationListAPIforDigitalPortals/model/inline_response2002_data_types.py
fds/sdk/RecommendationListAPIforDigitalPortals/model/inline_response2003.py
fds.sdk.RecommendationListAPIforDigitalPortals-0.10.2.dist-info/LICENSE
fds.sdk.RecommendationListAPIforDigitalPortals-0.10.2.dist-info/METADATA
fds.sdk.RecommendationListAPIforDigitalPortals-0.10.2.dist-info/WHEEL
fds.sdk.RecommendationListAPIforDigitalPortals-0.10.2.dist-info/top_level.txt
fds.sdk.RecommendationListAPIforDigitalPortals-0.10.2.dist-info/RECORD
